{
  "run_uuid": "CPvJ4VxSNhzTvpQ63rqELW",
  "seed": 0,
  "prefix": "ours_planning",
  "benchmark": "iron",
  "task": "craft_a_smithing_table",
  "goal": "smithing_table",
  "exp_num": 2009,
  "biome": "plains",
  "is_fixed_memory": false,
  "max_minutes": 10,
  "success": true,
  "status_detailed": "success",
  "video_file": "videos/v1/Iron_Craft_a_smithing_table/plains/success/2026_04_27_09_44_43_craft_smithing_table_CPvJ4VxSNhzTvpQ63rqELW.mp4",
  "steps": 6848,
  "minutes": 5.71,
  "metrics": {
    "chop a tree_0": {
      "SuccessMonitor": 1,
      "StepMonitor": 1444
    },
    "craft planks_1": {
      "SuccessMonitor": 1,
      "StepMonitor": 161
    },
    "craft crafting_table_2": {
      "SuccessMonitor": 1,
      "StepMonitor": 116
    },
    "craft stick_3": {
      "SuccessMonitor": 1,
      "StepMonitor": 94
    },
    "craft wooden_pickaxe_4": {
      "SuccessMonitor": 1,
      "StepMonitor": 321
    },
    "dig down and mine cobblestone_5": {
      "SuccessMonitor": 1,
      "StepMonitor": 892
    },
    "craft furnace_6": {
      "SuccessMonitor": 1,
      "StepMonitor": 440
    },
    "craft stone_pickaxe_7": {
      "SuccessMonitor": 1,
      "StepMonitor": 340
    },
    "dig down and mine iron_ore_8": {
      "SuccessMonitor": 1,
      "StepMonitor": 1688
    },
    "smelt iron_ingot_9": {
      "SuccessMonitor": 1,
      "StepMonitor": 1045
    },
    "craft smithing_table_10": {
      "SuccessMonitor": 1,
      "StepMonitor": 307
    }
  },
  "completed_subgoals": [
    {
      "task": "chop a tree",
      "goal": [
        "logs",
        7
      ]
    },
    {
      "task": "craft planks",
      "goal": [
        "planks",
        23
      ]
    },
    {
      "task": "craft crafting_table",
      "goal": [
        "crafting_table",
        1
      ]
    },
    {
      "task": "craft stick",
      "goal": [
        "stick",
        4
      ]
    },
    {
      "task": "craft wooden_pickaxe",
      "goal": [
        "wooden_pickaxe",
        1
      ]
    },
    {
      "task": "dig down and mine cobblestone",
      "goal": [
        "cobblestone",
        11
      ]
    },
    {
      "task": "craft furnace",
      "goal": [
        "furnace",
        1
      ]
    },
    {
      "task": "craft stone_pickaxe",
      "goal": [
        "stone_pickaxe",
        1
      ]
    },
    {
      "task": "dig down and mine iron_ore",
      "goal": [
        "iron_ore",
        2
      ]
    },
    {
      "task": "smelt iron_ingot",
      "goal": [
        "iron_ingot",
        2
      ]
    },
    {
      "task": "craft smithing_table",
      "goal": [
        "smithing_table",
        1
      ]
    }
  ],
  "completed_plans": [
    {
      "task": "chop a tree",
      "goal": [
        "logs",
        7
      ]
    },
    {
      "task": "craft planks",
      "goal": [
        "planks",
        23
      ]
    },
    {
      "task": "craft crafting_table",
      "goal": [
        "crafting_table",
        1
      ]
    },
    {
      "task": "craft stick",
      "goal": [
        "stick",
        4
      ]
    },
    {
      "task": "craft wooden_pickaxe",
      "goal": [
        "wooden_pickaxe",
        1
      ]
    },
    {
      "task": "dig down and mine cobblestone",
      "goal": [
        "cobblestone",
        11
      ]
    },
    {
      "task": "craft furnace",
      "goal": [
        "furnace",
        1
      ]
    },
    {
      "task": "craft stone_pickaxe",
      "goal": [
        "stone_pickaxe",
        1
      ]
    },
    {
      "task": "dig down and mine iron_ore",
      "goal": [
        "iron_ore",
        2
      ]
    },
    {
      "task": "smelt iron_ingot",
      "goal": [
        "iron_ingot",
        2
      ]
    },
    {
      "task": "craft smithing_table",
      "goal": [
        "smithing_table",
        1
      ]
    }
  ],
  "failed_subgoals": [],
  "remain_plans": [],
  "all_subgoals": [
    {
      "task": "chop a tree",
      "goal": [
        "logs",
        7
      ]
    },
    {
      "task": "craft planks",
      "goal": [
        "planks",
        23
      ]
    },
    {
      "task": "craft crafting_table",
      "goal": [
        "crafting_table",
        1
      ]
    },
    {
      "task": "craft stick",
      "goal": [
        "stick",
        4
      ]
    },
    {
      "task": "craft wooden_pickaxe",
      "goal": [
        "wooden_pickaxe",
        1
      ]
    },
    {
      "task": "dig down and mine cobblestone",
      "goal": [
        "cobblestone",
        11
      ]
    },
    {
      "task": "craft furnace",
      "goal": [
        "furnace",
        1
      ]
    },
    {
      "task": "craft stone_pickaxe",
      "goal": [
        "stone_pickaxe",
        1
      ]
    },
    {
      "task": "dig down and mine iron_ore",
      "goal": [
        "iron_ore",
        2
      ]
    },
    {
      "task": "smelt iron_ingot",
      "goal": [
        "iron_ingot",
        2
      ]
    },
    {
      "task": "craft smithing_table",
      "goal": [
        "smithing_table",
        1
      ]
    }
  ],
  "all_plans": [
    {
      "task": "chop a tree",
      "goal": [
        "logs",
        7
      ]
    },
    {
      "task": "craft planks",
      "goal": [
        "planks",
        23
      ]
    },
    {
      "task": "craft crafting_table",
      "goal": [
        "crafting_table",
        1
      ]
    },
    {
      "task": "craft stick",
      "goal": [
        "stick",
        4
      ]
    },
    {
      "task": "craft wooden_pickaxe",
      "goal": [
        "wooden_pickaxe",
        1
      ]
    },
    {
      "task": "dig down and mine cobblestone",
      "goal": [
        "cobblestone",
        11
      ]
    },
    {
      "task": "craft furnace",
      "goal": [
        "furnace",
        1
      ]
    },
    {
      "task": "craft stone_pickaxe",
      "goal": [
        "stone_pickaxe",
        1
      ]
    },
    {
      "task": "dig down and mine iron_ore",
      "goal": [
        "iron_ore",
        2
      ]
    },
    {
      "task": "smelt iron_ingot",
      "goal": [
        "iron_ingot",
        2
      ]
    },
    {
      "task": "craft smithing_table",
      "goal": [
        "smithing_table",
        1
      ]
    }
  ],
  "failed_waypoints": []
}